Metadata-Version: 2.1
Name: ntt-json-model
Version: 1.0.2
Summary: Small library for observation mechanism
Home-page: https://github.com/threezinedine/ntt-json-model
Author: threezinedine
Author-email: threezinedine@email.com
License: UNKNOWN
Project-URL: Source, https://github.com/threezinedine/ntt-json-model
Project-URL: Tracker, https://github.com/threezinedine/ntt-json-model/issues
Keywords: json,mvvm,signal,ntt
Platform: UNKNOWN
Classifier: Development Status :: 3 - Alpha
Classifier: Intended Audience :: Developers
Classifier: Programming Language :: Python :: 3
Classifier: Programming Language :: Python :: 3.6
Classifier: Programming Language :: Python :: 3.7
Classifier: Programming Language :: Python :: 3.8
Classifier: Programming Language :: Python :: 3.9
License-File: LICENSE
Requires-Dist: ntt-signal
Requires-Dist: ntt-observable-list
